_netgraph_core.cpython-312-darwin.so
netgraph_core-0.3.2.dist-info/RECORD
netgraph_core-0.3.2.dist-info/WHEEL
netgraph_core-0.3.2.dist-info/METADATA
netgraph_core-0.3.2.dist-info/licenses/LICENSE
netgraph_core/_version.py
netgraph_core/__init__.py
netgraph_core/_docs.py
netgraph_core/py.typed
