Metadata-Version: 2.2
Name: netgraph-core
Version: 0.3.2
Summary: C++ implementation of graph algorithms for network flow analysis and traffic engineering with Python bindings
Author: Project Contributors
License: AGPL-3.0-or-later
Classifier: Development Status :: 3 - Alpha
Classifier: Intended Audience :: Developers
Classifier: Intended Audience :: Science/Research
Classifier: Topic :: Scientific/Engineering
Classifier: Topic :: Software Development :: Libraries :: Python Modules
Classifier: License :: OSI Approved :: GNU Affero General Public License v3 or later (AGPLv3+)
Classifier: Programming Language :: Python :: 3
Classifier: Programming Language :: Python :: 3.11
Classifier: Programming Language :: Python :: 3.12
Classifier: Programming Language :: Python :: 3.13
Classifier: Programming Language :: Python :: 3 :: Only
Classifier: Programming Language :: C++
Classifier: Programming Language :: Python :: Implementation :: CPython
Classifier: Operating System :: OS Independent
Project-URL: Homepage, https://github.com/networmix/NetGraph-Core
Requires-Python: >=3.11
Requires-Dist: numpy>=1.22
Provides-Extra: dev
Requires-Dist: pytest>=8; extra == "dev"
Requires-Dist: pytest-cov; extra == "dev"
Requires-Dist: pytest-benchmark; extra == "dev"
Requires-Dist: gcovr>=7; extra == "dev"
Requires-Dist: ruff==0.11.13; extra == "dev"
Requires-Dist: pyright==1.1.401; extra == "dev"
Requires-Dist: pre-commit; extra == "dev"
Requires-Dist: build; extra == "dev"
Requires-Dist: twine; extra == "dev"
Requires-Dist: cmake>=3.23; extra == "dev"
Requires-Dist: ninja; extra == "dev"
